rl_test_common/__init__.py
rl_test_common/common.py
rl_test_common/config.py
rl_test_common/singleton_meta.py
rl_test_common/exceptions/__init__.py
rl_test_common/exceptions/empty_config_value.py
rl_test_common/exceptions/invalid_config_value.py
rl_test_common-0.1.4.dist-info/METADATA
rl_test_common-0.1.4.dist-info/WHEEL
rl_test_common-0.1.4.dist-info/top_level.txt
rl_test_common-0.1.4.dist-info/RECORD
