Metadata-Version: 2.1
Name: rl-test-common
Version: 0.1.4
Summary: Common
Author: Antonio Corluka
Author-email: antonio.corluka@outlook.com
Requires-Python: >=3.11
Requires-Dist: psutil
